src/fontina/__init__.py
src/fontina/adobevfr_dataset.py
src/fontina/augmentation_utils.py
src/fontina/augmented_dataset.py
src/fontina/config.py
src/fontina/generate.py
src/fontina/predict.py
src/fontina/train.py
src/fontina/models/__init__.py
src/fontina/models/deepfont.py
src/fontina/models/lightning_generate_callback.py
src/fontina/models/lightning_wrappers.py
fontina-0.0.1.dist-info/LICENSE
fontina-0.0.1.dist-info/METADATA
fontina-0.0.1.dist-info/WHEEL
fontina-0.0.1.dist-info/entry_points.txt
fontina-0.0.1.dist-info/top_level.txt
fontina-0.0.1.dist-info/RECORD
