Metadata-Version: 2.1
Name: fontina
Version: 0.0.1
Summary: Visual font recognition (VFR) library
Author-email: Alessio Placitelli <a.placitelli@a2p.it>
License: MIT
Project-URL: Homepage, https://github.com/Dexterp37/fontina
Project-URL: Bug Tracker, https://github.com/Dexterp37/fontina/issues
Requires-Python: >=3.10
License-File: LICENSE
Requires-Dist: albumentations ==1.3.1
Requires-Dist: trdg ==1.8.0
Requires-Dist: pillow ==9.5.0
Requires-Dist: pytorch-lightning[extra] ==2.0.8
Requires-Dist: pyyaml ==6.0.1
Requires-Dist: rstr ==3.2.1
Requires-Dist: torch ==2.0.1
Requires-Dist: torchvision ==0.15.2
Provides-Extra: linting
Requires-Dist: black ==23.7.0 ; extra == 'linting'
Requires-Dist: flake8 ==6.1.0 ; extra == 'linting'
Requires-Dist: flake8-bugbear ==23.7.10 ; extra == 'linting'
Requires-Dist: mypy ==1.4.1 ; extra == 'linting'
Requires-Dist: pytest ==7.4.0 ; extra == 'linting'
Requires-Dist: types-PyYAML ==6.0.1 ; extra == 'linting'
Requires-Dist: types-pillow ==9.5.0 ; extra == 'linting'
